js_loader/__init__.py
js_loader-0.2.2.dist-info/METADATA
js_loader-0.2.2.dist-info/WHEEL
js_loader-0.2.2.dist-info/top_level.txt
js_loader-0.2.2.dist-info/RECORD
