Metadata-Version: 2.2
Name: js-loader
Version: 0.2.2
Summary: Load javascript files as python modules
Author: Hans Then
Author-email: hans.then@gmail.com
Requires-Python: >=3.7
Dynamic: author
Dynamic: author-email
Dynamic: description
Dynamic: description-content-type
Dynamic: requires-python
Dynamic: summary
